uiform/__init__.py
uiform/_resource.py
uiform/client.py
uiform/py.typed
uiform/_utils/__init__.py
uiform/_utils/ai_model.py
uiform/_utils/ai_models.py
uiform/_utils/benchmarking copy.py
uiform/_utils/benchmarking.py
uiform/_utils/chat.py
uiform/_utils/display.py
uiform/_utils/json_schema.py
uiform/_utils/mime.py
uiform/_utils/responses.py
uiform/_utils/stream_context_managers.py
uiform/_utils/usage/__init__.py
uiform/_utils/usage/anthropic.py
uiform/_utils/usage/gemini.py
uiform/_utils/usage/openai.py
uiform/_utils/usage/usage.py
uiform/_utils/usage/xai.py
uiform/resources/AsyncEvals.py
uiform/resources/__init__.py
uiform/resources/completions.py
uiform/resources/completions_stream.py
uiform/resources/evals.py
uiform/resources/files.py
uiform/resources/finetuning.py
uiform/resources/jsonlUtils.py
uiform/resources/logs.py
uiform/resources/models.py
uiform/resources/openai_example.py
uiform/resources/prompt_optimization.py
uiform/resources/responses.py
uiform/resources/responses_stream.py
uiform/resources/schemas.py
uiform/resources/usage.py
uiform/resources/automations/__init__.py
uiform/resources/automations/client.py
uiform/resources/automations/endpoints.py
uiform/resources/automations/links.py
uiform/resources/automations/mailboxes.py
uiform/resources/automations/outlook.py
uiform/resources/consensus/__init__.py
uiform/resources/consensus/client.py
uiform/resources/consensus/completions.py
uiform/resources/consensus/completions_stream.py
uiform/resources/consensus/responses.py
uiform/resources/consensus/responses_stream.py
uiform/resources/db/__init__.py
uiform/resources/db/annotations.py
uiform/resources/db/client.py
uiform/resources/db/dataset_memberships.py
uiform/resources/db/datasets.py
uiform/resources/db/files.py
uiform/resources/deployments/__init__.py
uiform/resources/deployments/client.py
uiform/resources/deployments/endpoints.py
uiform/resources/deployments/links.py
uiform/resources/deployments/logs.py
uiform/resources/deployments/mailboxes.py
seaside-0.0.33.dist-info/METADATA
seaside-0.0.33.dist-info/WHEEL
seaside-0.0.33.dist-info/top_level.txt
seaside-0.0.33.dist-info/RECORD
